nuqql_based/__init__.py
nuqql_based/account.py
nuqql_based/based.py
nuqql_based/callback.py
nuqql_based/config.py
nuqql_based/logger.py
nuqql_based/main.py
nuqql_based/message.py
nuqql_based/py.typed
nuqql_based/server.py
nuqql_based-0.3.0.dist-info/LICENSE
nuqql_based-0.3.0.dist-info/METADATA
nuqql_based-0.3.0.dist-info/WHEEL
nuqql_based-0.3.0.dist-info/entry_points.txt
nuqql_based-0.3.0.dist-info/top_level.txt
nuqql_based-0.3.0.dist-info/RECORD
