Metadata-Version: 2.1
Name: nuqql-based
Version: 0.3.0
Summary: Basic network daemon library for nuqql
Home-page: https://github.com/hwipl/nuqql-based
Author: hwipl
Author-email: nuqql-based@hwipl.net
License: MIT
Platform: UNKNOWN
Classifier: Programming Language :: Python :: 3
Classifier: License :: OSI Approved :: MIT License
Requires-Python: >=3.7
